{
    "title": "קדיש יתום | Mourner's Ḳaddish, an interpretive rhyming translation by Alan Wagman",
    "author": "Alan Wagman (translation)",
    "coauthors": [
        {
            "name": "Alan Wagman (translation)",
            "bio": "Alan Wagman is an assistant public defender in Albuquerque.",
            "website": "",
            "avatar": "https://opensiddur.org/wp-content/uploads/2014/11/Alan-Wagman-96x96.jpg",
            "profile_link": "https://opensiddur.org/profile/alan-wagman"
        }
    ],
    "date": "2013-04-02",
    "last_updated": "2025-02-02",
    "excerpt": "This is an English language interpretation of Kaddish, intended to capture the spirit of translations/interpretations that I have seen in various sources and also to capture the sound and rhythm of the Aramaic text, including syllables which, when read simultaneously with the Aramaic, rhyme with the Aramaic. . . .",
    "content": "\n<table style=\"margin-left: auto; margin-right: auto;\" class=\"draggable toggleable-table\">\n<thead>\n<tr>\n<th id=\"x\" style=\"text-align: right;\">Source (Hebrew)</th>\n<th style=\"text-align: left;\">Translation (English)</th>\n</tr>\n</thead>\n<tbody>\n<tr>\n<td style=\"vertical-align:top;\">\n<div class=\"liturgy\" lang=\"he\">\nיִתְגַּדַּל וְיִתְקַדַּשׁ שְׁמֵהּ רַבָּא.<br />\nבְּעָלְמָא דִּי בְרָא כִרְעוּתֵהּ<br />\nוְיַמְלִיךְ מַלְכוּתֵהּ,<br />\nבְּחַיֵּיכוֺן<br />\nוּבְיוֹמֵיכוֹן<br />\nוּבְחַיֵּי דְכָל בֵּית יִשְׂרָאֵל,<br />\nבַּעֲגָלָא וּבִזְמַן קָרִיב.<br />\nוְאִמְרוּ אָמֵן׃<br />\n</span></div>\n</td>\n<td style=\"vertical-align:top;\">\n<div class=\"english\" lang=\"en\">\nIt is all and won’t be lost, the Holy Name (<em>amein</em>).<br />\nWe all make Divine words of praise<br />\nfor here lead all true ways.<br />\nAfar yet home<br />\nwe are going home<br />\nand seek the way to our home, Yisrael.<br />\nInto lives You come and never leave.<br />\nBlessed be You, <em>Amein</em>.\n</div>\n</td>\n</tr>\n<tr>\n<td style=\"vertical-align:top;\">\n<div class=\"liturgy\" lang=\"he\">\nיְהֵא שְׁמֵהּ רַבָּא מְבָרַךְ לְעָלַם וּלְעָלְמֵי עָלְמַיָּא׃<br />\n</span></div>\n</td>\n<td style=\"vertical-align:top;\">\n<div class=\"english\" lang=\"en\">\nWe say the Name Oneness and we hear of the time when we may all know Yah.\n</div>\n</td>\n</tr>\n<tr>\n<td style=\"vertical-align:top;\">\n<div class=\"liturgy\" lang=\"he\">\nיִתְבָּרַךְ,<br />\nוְיִשְׁתַּבַּח, וְיִתְפָּאֵר,<br />\nוְיִתְרוֹמֵם,<br />\nוְיִתְנַשּׂא,<br />\nוְיִתְהַדָּר,<br />\nוְיִתְעַלֶּה,<br />\nוְיִתְהַלָּל,<br />\nשְׁמֵהּ דְקֻדְשָׁא בְּרִיךְ הוּא.<br />\nלְעֵלָּא מִן כָּל בִּרְכָתָא<br />\nוְשִׁירָתָא,<br />\nתֻּשְׁבְּחָתָא<br />\nוְנֶחֱמָתָא,<br />\nדַּאֲמִירָן בְּעָלְמָא,<br />\nוְאִמְרוּ אָמֵן׃<br />\n</span></div>\n</td>\n<td style=\"vertical-align:top;\">\n<div class=\"english\" lang=\"en\">\nBeyond a sigh,<br />\nthe reason why or Reason’s “Why?”,<br />\nmagnify<br />\nand glorify<br />\nand sanctify,<br />\npraise to the sky,<br />\npraise low and high,<br />\nthe Name of Holy Awe, We Bless You,<br />\nWho gives law,<br />\nbreathes life into law,<br />\nlaw filled with awe,<br />\nholy law from which we don’t withdraw<br />\nbut breathe deep into the soul.<br />\nBlessed be You, <em>Amein</em>.\n</div>\n</td>\n</tr>\n<tr>\n<td style=\"vertical-align:top;\">\n<div class=\"liturgy\" lang=\"he\">\nיְהֵא שְׁלָמָה רַבָּא מִן שְׁמַיָּא וְחַיִּים<br />\nוְעַל כָּל יִשְֹרָאֵל,<br />\nוְאִמְרוּ אָמֵן׃<br />\n</span></div>\n</td>\n<td style=\"vertical-align:top;\">\n<div class=\"english\" lang=\"en\">\nWe pray, hush be silent, when all are here and all are gone,<br />\nmay You bless all of Yisrael.<br />\nBlessed be You, <em>Amein</em>.\n</div>\n</td>\n</tr>\n<tr>\n<td style=\"vertical-align:top;\">\n<div class=\"liturgy\" lang=\"he\">\nעוֹשֶׂה שָׁלוֹם בִּמְרוֹמָיו<br />\n הוּא יַעֲשֶׂה שָׁלוֹם עָלֵינוּ<br />\n(וְעַל כָּל יִשְׂרָאֵל)<br />\nוְעַל כָּל יוֺשְׁבֵי תֵבֶל<br />\n וְאִמְרוּ אָמֵן׃<br />\n</span></div>\n</td>\n<td style=\"vertical-align:top;\">\n<div class=\"english\" lang=\"en\">\nOh, say, “Shalom,” this is love,<br />\nand when we say, “Shalom,” we name You,<br />\njoined with all Yisrael,<br />\n(and all the world).<br />\nBlessed be You, <em>Amein</em>.\n</td>\n</tr>\n</tbody>\n</table>\n<hr />\n<p>This is an English language interpretation of the Mourner&#8217;s Ḳaddish, intended to capture the spirit of translations/interpretations that I have seen in various sources and also to capture the sound and rhythm of the Aramaic text, including syllables which, when read simultaneously with the Aramaic, rhyme with the Aramaic.</p>\n",
    "categories": [
        "Mourning",
        "Ḳaddish"
    ],
    "tags": [
        "21st century C.E.",
        "58th century A.M.",
        "interpretive translation",
        "prayers of orphans",
        "rhyming translation",
        "קדיש יתום Mourner's Ḳaddish"
    ],
    "custom_fields": {
        "open_content_license": [
            "<a href='https://creativecommons.org/licenses/by/4.0/'>Creative Commons Attribution (CC BY) 4.0 International</a> free-culture license"
        ],
        "_yoast_wpseo_primary_category": [
            "764"
        ],
        "_thumbnail_id": [
            "30362"
        ]
    },
    "featured_image": {
        "url": "https://opensiddur.org/wp-content/uploads/2020/02/Kaddish.png",
        "title": "ḲADDISH",
        "caption": "\"ḲADDISH\" adapted by Aharon Varady from the cover art for Allen Ginsberg's \"Kaddish for Naomi Ginsberg (1894-1956)\" "
    },
    "source_link": "https://opensiddur.org/?p=6613",
    "permalink": "https://opensiddur.org/prayers/life-cycle/death/mourning/kaddish-an-interpretative-rhyming-translation-by-alan-wagman/",
    "slug": "kaddish-an-interpretative-rhyming-translation-by-alan-wagman"
}